{"arg":[{"code":"EUR","rateInArs":992.215,"rateDetails":{"buy":991.49,"sell":992.94,"average":992.215}},{"code":"USD","rateInArs":914.5,"rateDetails":{"buy":894.5,"sell":934.5,"average":914.5}},{"code":"USD_BLUE","rateInArs":1410,"rateDetails":{"buy":1400,"sell":1420,"average":1410}},{"code":"USD_MEP","rateInArs":1395.9,"rateDetails":{"buy":1394.6,"sell":1397.2,"average":1395.9}},{"code":"USD_CCL","rateInArs":1394.35,"rateDetails":{"buy":1391.8,"sell":1396.9,"average":1394.35}}],"all":[{"code":"AED","rateInUsd":3.671481},{"code":"AFN","rateInUsd":71.003011},{"code":"ALL","rateInUsd":92.257221},{"code":"AMD","rateInUsd":385.812991},{"code":"ANG","rateInUsd":1.7839},{"code":"AOA","rateInUsd":870.404737},{"code":"ARS","rateInUsd":914.721731},{"code":"AUD","rateInUsd":1.4809},{"code":"AWG","rateInUsd":1.79},{"code":"AZN","rateInUsd":1.7},{"code":"BAM","rateInUsd":1.80347},{"code":"BBD","rateInUsd":2},{"code":"BDT","rateInUsd":117.45993},{"code":"BGN","rateInUsd":1.80044},{"code":"BHD","rateInUsd":0.376},{"code":"BIF","rateInUsd":2883.187418},{"code":"BMD","rateInUsd":1},{"code":"BND","rateInUsd":1.34797},{"code":"BOB","rateInUsd":6.926361},{"code":"BRL","rateInUsd":5.458551},{"code":"BSD","rateInUsd":1},{"code":"BTN","rateInUsd":83.502296},{"code":"BWP","rateInUsd":13.522491},{"code":"BYN","rateInUsd":3.274954},{"code":"BYR","rateInUsd":32749.509879},{"code":"BZD","rateInUsd":2},{"code":"CAD","rateInUsd":1.36353},{"code":"CDF","rateInUsd":2863.249115},{"code":"CHF","rateInUsd":0.89524},{"code":"CLF","rateInUsd":0.02442},{"code":"CLP","rateInUsd":937.2275},{"code":"CNY","rateInUsd":7.262651},{"code":"COP","rateInUsd":4080.846345},{"code":"CRC","rateInUsd":530.521127},{"code":"CUC","rateInUsd":1},{"code":"CUP","rateInUsd":24},{"code":"CVE","rateInUsd":101.733987},{"code":"CZK","rateInUsd":23.184832},{"code":"DJF","rateInUsd":177.721},{"code":"DKK","rateInUsd":6.878331},{"code":"DOP","rateInUsd":58.990451},{"code":"DZD","rateInUsd":135.039236},{"code":"EGP","rateInUsd":47.991499},{"code":"ERN","rateInUsd":15},{"code":"ETB","rateInUsd":57.668667},{"code":"EUR","rateInUsd":0.92235},{"code":"FJD","rateInUsd":2.22727},{"code":"FKP","rateInUsd":0.780595},{"code":"GBP","rateInUsd":0.78037},{"code":"GEL","rateInUsd":2.75926},{"code":"GGP","rateInUsd":0.780595},{"code":"GHS","rateInUsd":15.393892},{"code":"GIP","rateInUsd":0.780595},{"code":"GMD","rateInUsd":57.804917},{"code":"GNF","rateInUsd":8596.591488},{"code":"GTQ","rateInUsd":7.744821},{"code":"GYD","rateInUsd":208.647278},{"code":"HKD","rateInUsd":7.809201},{"code":"HNL","rateInUsd":24.725973},{"code":"HRK","rateInUsd":6.606181},{"code":"HTG","rateInUsd":134.290861},{"code":"HUF","rateInUsd":362.814819},{"code":"IDR","rateInUsd":16253.69958},{"code":"ILS","rateInUsd":3.68725},{"code":"IMP","rateInUsd":0.780595},{"code":"INR","rateInUsd":83.448454},{"code":"IQD","rateInUsd":1308.104264},{"code":"IRR","rateInUsd":41944.211236},{"code":"ISK","rateInUsd":138.147433},{"code":"JEP","rateInUsd":0.780595},{"code":"JMD","rateInUsd":156.667076},{"code":"JOD","rateInUsd":0.71},{"code":"JPY","rateInUsd":160.741374},{"code":"KES","rateInUsd":128.126689},{"code":"KGS","rateInUsd":85.710733},{"code":"KHR","rateInUsd":4113.161605},{"code":"KMF","rateInUsd":454.490671},{"code":"KPW","rateInUsd":900.001494},{"code":"KRW","rateInUsd":1375.22358},{"code":"KWD","rateInUsd":0.30503},{"code":"KYD","rateInUsd":0.83333},{"code":"KZT","rateInUsd":478.070204},{"code":"LAK","rateInUsd":22095.130047},{"code":"LBP","rateInUsd":89561.839634},{"code":"LKR","rateInUsd":303.576475},{"code":"LRD","rateInUsd":194.731781},{"code":"LSL","rateInUsd":18.198063},{"code":"LTL","rateInUsd":3.182551},{"code":"LVL","rateInUsd":0.647792},{"code":"LYD","rateInUsd":4.858781},{"code":"MAD","rateInUsd":9.861882},{"code":"MDL","rateInUsd":17.649853},{"code":"MGA","rateInUsd":4478.162312},{"code":"MKD","rateInUsd":56.92264},{"code":"MMK","rateInUsd":2092.286371},{"code":"MNT","rateInUsd":3387.007494},{"code":"MOP","rateInUsd":8.002031},{"code":"MRO","rateInUsd":356.999828},{"code":"MUR","rateInUsd":47.171255},{"code":"MVR","rateInUsd":15.450783},{"code":"MWK","rateInUsd":1731.21092},{"code":"MXN","rateInUsd":18.067273},{"code":"MYR","rateInUsd":4.709541},{"code":"MZN","rateInUsd":64.045042},{"code":"NAD","rateInUsd":18.127282},{"code":"NGN","rateInUsd":1514.105379},{"code":"NIO","rateInUsd":36.624445},{"code":"NOK","rateInUsd":10.549691},{"code":"NPR","rateInUsd":133.190549},{"code":"NZD","rateInUsd":1.6261},{"code":"OMR","rateInUsd":0.38359},{"code":"PAB","rateInUsd":0.99874},{"code":"PEN","rateInUsd":3.796321},{"code":"PGK","rateInUsd":3.84077},{"code":"PHP","rateInUsd":58.453708},{"code":"PKR","rateInUsd":278.588369},{"code":"PLN","rateInUsd":3.947631},{"code":"PYG","rateInUsd":7549.838851},{"code":"QAR","rateInUsd":3.64052},{"code":"RON","rateInUsd":4.589111},{"code":"RSD","rateInUsd":107.605461},{"code":"RUB","rateInUsd":87.992525},{"code":"RWF","rateInUsd":1306.637257},{"code":"SAR","rateInUsd":3.747261},{"code":"SBD","rateInUsd":8.435294},{"code":"SCR","rateInUsd":14.651143},{"code":"SDG","rateInUsd":601.5},{"code":"SEK","rateInUsd":10.474072},{"code":"SGD","rateInUsd":1.34691},{"code":"SHP","rateInUsd":0.78037},{"code":"SLL","rateInUsd":22438.023151},{"code":"SOS","rateInUsd":570.638007},{"code":"SRD","rateInUsd":30.219204},{"code":"STD","rateInUsd":22648.774406},{"code":"SVC","rateInUsd":8.75},{"code":"SYP","rateInUsd":13001.868696},{"code":"SZL","rateInUsd":18.202823},{"code":"THB","rateInUsd":36.540337},{"code":"TJS","rateInUsd":10.616802},{"code":"TMT","rateInUsd":3.5},{"code":"TND","rateInUsd":3.130161},{"code":"TOP","rateInUsd":2.32562},{"code":"TRY","rateInUsd":32.642794},{"code":"TTD","rateInUsd":6.746061},{"code":"TWD","rateInUsd":32.434824},{"code":"TZS","rateInUsd":2649.163424},{"code":"UAH","rateInUsd":40.625236},{"code":"UGX","rateInUsd":3690.718265},{"code":"USD","rateInUsd":1},{"code":"UYU","rateInUsd":39.956388},{"code":"UZS","rateInUsd":12625.54364},{"code":"VEF","rateInUsd":3646595.7788},{"code":"VND","rateInUsd":25378.441103},{"code":"VUV","rateInUsd":118.271835},{"code":"WST","rateInUsd":2.725522},{"code":"XAF","rateInUsd":604.950759},{"code":"XCD","rateInUsd":2.7},{"code":"XOF","rateInUsd":604.950754},{"code":"XPF","rateInUsd":109.99027},{"code":"YER","rateInUsd":249.973122},{"code":"ZAR","rateInUsd":18.198213},{"code":"ZMK","rateInUsd":9001.2},{"code":"ZMW","rateInUsd":24.510204},{"code":"ZWL","rateInUsd":13.678269}],"updatedAt":1720335608289}