{"arg":[{"code":"EUR","rateInArs":971.37,"rateDetails":{"buy":970.92,"sell":971.82,"average":971.37}},{"code":"USD","rateInArs":918,"rateDetails":{"buy":918,"sell":918,"average":918}},{"code":"USD_BLUE","rateInArs":1255,"rateDetails":{"buy":1245,"sell":1265,"average":1255}},{"code":"USD_MEP","rateInArs":1281.65,"rateDetails":{"buy":1279.4,"sell":1283.9,"average":1281.65}},{"code":"USD_CCL","rateInArs":1305.25,"rateDetails":{"buy":1303.2,"sell":1307.3,"average":1305.25}}],"all":[{"code":"AED","rateInUsd":3.67139},{"code":"AFN","rateInUsd":70.29024},{"code":"ALL","rateInUsd":92.497837},{"code":"AMD","rateInUsd":389.730727},{"code":"ANG","rateInUsd":1.7862},{"code":"AOA","rateInUsd":852.133413},{"code":"ARS","rateInUsd":898.745028},{"code":"AUD","rateInUsd":1.5186},{"code":"AWG","rateInUsd":1.79},{"code":"AZN","rateInUsd":1.7},{"code":"BAM","rateInUsd":1.80959},{"code":"BBD","rateInUsd":2},{"code":"BDT","rateInUsd":117.556974},{"code":"BGN","rateInUsd":1.79226},{"code":"BHD","rateInUsd":0.376},{"code":"BIF","rateInUsd":2872.339184},{"code":"BMD","rateInUsd":1},{"code":"BND","rateInUsd":1.35109},{"code":"BOB","rateInUsd":6.922881},{"code":"BRL","rateInUsd":5.350911},{"code":"BSD","rateInUsd":1},{"code":"BTN","rateInUsd":83.541745},{"code":"BWP","rateInUsd":13.808232},{"code":"BYN","rateInUsd":3.275005},{"code":"BYR","rateInUsd":32750.046739},{"code":"BZD","rateInUsd":2},{"code":"CAD","rateInUsd":1.37598},{"code":"CDF","rateInUsd":2811.950813},{"code":"CHF","rateInUsd":0.89587},{"code":"CLF","rateInUsd":0.02412},{"code":"CLP","rateInUsd":919.697104},{"code":"CNY","rateInUsd":7.244321},{"code":"COP","rateInUsd":3935.266267},{"code":"CRC","rateInUsd":514.969759},{"code":"CUC","rateInUsd":1},{"code":"CUP","rateInUsd":24},{"code":"CVE","rateInUsd":102.034704},{"code":"CZK","rateInUsd":22.793473},{"code":"DJF","rateInUsd":177.721},{"code":"DKK","rateInUsd":6.904171},{"code":"DOP","rateInUsd":59.32712},{"code":"DZD","rateInUsd":135.062845},{"code":"EGP","rateInUsd":47.519088},{"code":"ERN","rateInUsd":15},{"code":"ETB","rateInUsd":57.813086},{"code":"EUR","rateInUsd":0.92536},{"code":"FJD","rateInUsd":2.27111},{"code":"FKP","rateInUsd":0.785708},{"code":"GBP","rateInUsd":0.7859},{"code":"GEL","rateInUsd":2.82348},{"code":"GGP","rateInUsd":0.785708},{"code":"GHS","rateInUsd":14.840971},{"code":"GIP","rateInUsd":0.785707},{"code":"GMD","rateInUsd":58.214686},{"code":"GNF","rateInUsd":8586.249732},{"code":"GTQ","rateInUsd":7.754861},{"code":"GYD","rateInUsd":209.023707},{"code":"HKD","rateInUsd":7.808602},{"code":"HNL","rateInUsd":24.691733},{"code":"HRK","rateInUsd":6.653011},{"code":"HTG","rateInUsd":134.725704},{"code":"HUF","rateInUsd":361.914637},{"code":"IDR","rateInUsd":16171.108671},{"code":"ILS","rateInUsd":3.75658},{"code":"IMP","rateInUsd":0.785708},{"code":"INR","rateInUsd":83.36648},{"code":"IQD","rateInUsd":1306.657586},{"code":"IRR","rateInUsd":41997.759005},{"code":"ISK","rateInUsd":137.484202},{"code":"JEP","rateInUsd":0.785707},{"code":"JMD","rateInUsd":155.380671},{"code":"JOD","rateInUsd":0.71},{"code":"JPY","rateInUsd":156.754426},{"code":"KES","rateInUsd":129.632354},{"code":"KGS","rateInUsd":87.24174},{"code":"KHR","rateInUsd":4107.754866},{"code":"KMF","rateInUsd":454.422723},{"code":"KPW","rateInUsd":900.001021},{"code":"KRW","rateInUsd":1377.191924},{"code":"KWD","rateInUsd":0.30604},{"code":"KYD","rateInUsd":0.83333},{"code":"KZT","rateInUsd":446.962184},{"code":"LAK","rateInUsd":21555.216945},{"code":"LBP","rateInUsd":89522.422202},{"code":"LKR","rateInUsd":303.967258},{"code":"LRD","rateInUsd":194.283404},{"code":"LSL","rateInUsd":18.906582},{"code":"LTL","rateInUsd":3.193153},{"code":"LVL","rateInUsd":0.64995},{"code":"LYD","rateInUsd":4.831091},{"code":"MAD","rateInUsd":9.907741},{"code":"MDL","rateInUsd":17.514282},{"code":"MGA","rateInUsd":4496.287428},{"code":"MKD","rateInUsd":56.870879},{"code":"MMK","rateInUsd":2094.245161},{"code":"MNT","rateInUsd":3387.194342},{"code":"MOP","rateInUsd":8.065981},{"code":"MRO","rateInUsd":356.999828},{"code":"MUR","rateInUsd":45.748149},{"code":"MVR","rateInUsd":15.449342},{"code":"MWK","rateInUsd":1742.830879},{"code":"MXN","rateInUsd":18.421133},{"code":"MYR","rateInUsd":4.688571},{"code":"MZN","rateInUsd":63.570188},{"code":"NAD","rateInUsd":18.813062},{"code":"NGN","rateInUsd":1485.103542},{"code":"NIO","rateInUsd":36.624488},{"code":"NOK","rateInUsd":10.707621},{"code":"NPR","rateInUsd":134.137057},{"code":"NZD","rateInUsd":1.63787},{"code":"OMR","rateInUsd":0.38402},{"code":"PAB","rateInUsd":0.99883},{"code":"PEN","rateInUsd":3.754061},{"code":"PGK","rateInUsd":3.835911},{"code":"PHP","rateInUsd":58.683786},{"code":"PKR","rateInUsd":278.101008},{"code":"PLN","rateInUsd":3.992131},{"code":"PYG","rateInUsd":7549.391238},{"code":"QAR","rateInUsd":3.63861},{"code":"RON","rateInUsd":4.604471},{"code":"RSD","rateInUsd":107.991024},{"code":"RUB","rateInUsd":89.016306},{"code":"RWF","rateInUsd":1300.535375},{"code":"SAR","rateInUsd":3.74446},{"code":"SBD","rateInUsd":8.230467},{"code":"SCR","rateInUsd":14.615662},{"code":"SDG","rateInUsd":601.5},{"code":"SEK","rateInUsd":10.530952},{"code":"SGD","rateInUsd":1.35022},{"code":"SHP","rateInUsd":0.7859},{"code":"SLL","rateInUsd":22432.906643},{"code":"SOS","rateInUsd":571.009863},{"code":"SRD","rateInUsd":31.589015},{"code":"STD","rateInUsd":22499.896588},{"code":"SVC","rateInUsd":8.75},{"code":"SYP","rateInUsd":12994.727867},{"code":"SZL","rateInUsd":18.838683},{"code":"THB","rateInUsd":36.788045},{"code":"TJS","rateInUsd":10.790611},{"code":"TMT","rateInUsd":3.5},{"code":"TND","rateInUsd":3.10166},{"code":"TOP","rateInUsd":2.32395},{"code":"TRY","rateInUsd":32.354393},{"code":"TTD","rateInUsd":6.728541},{"code":"TWD","rateInUsd":32.428355},{"code":"TZS","rateInUsd":2616.513624},{"code":"UAH","rateInUsd":40.272396},{"code":"UGX","rateInUsd":3791.187542},{"code":"USD","rateInUsd":1},{"code":"UYU","rateInUsd":38.868157},{"code":"UZS","rateInUsd":12644.784246},{"code":"VEF","rateInUsd":3643350.614234},{"code":"VND","rateInUsd":25392.206836},{"code":"VUV","rateInUsd":118.189803},{"code":"WST","rateInUsd":2.719608},{"code":"XAF","rateInUsd":607.148645},{"code":"XCD","rateInUsd":2.7},{"code":"XOF","rateInUsd":607.148631},{"code":"XPF","rateInUsd":110.358147},{"code":"YER","rateInUsd":249.812594},{"code":"ZAR","rateInUsd":18.838293},{"code":"ZMK","rateInUsd":9001.2},{"code":"ZMW","rateInUsd":26.456233},{"code":"ZWL","rateInUsd":13.398145}],"updatedAt":1717894803949}