{"arg":[{"code":"EUR","rateInArs":907.91,"rateDetails":{"buy":907.69,"sell":908.13,"average":907.91}},{"code":"USD","rateInArs":837.5,"rateDetails":{"buy":817.5,"sell":857.5,"average":837.5}},{"code":"USD_BLUE","rateInArs":1075,"rateDetails":{"buy":1065,"sell":1085,"average":1075}},{"code":"USD_MEP","rateInArs":1074.45,"rateDetails":{"buy":1072.6,"sell":1076.3,"average":1074.45}},{"code":"USD_CCL","rateInArs":1091.4,"rateDetails":{"buy":1081.7,"sell":1101.1,"average":1091.4}}],"all":[{"code":"AED","rateInUsd":3.671771},{"code":"AFN","rateInUsd":73.65801},{"code":"ALL","rateInUsd":95.764439},{"code":"AMD","rateInUsd":404.660157},{"code":"ANG","rateInUsd":1.78615},{"code":"AOA","rateInUsd":829.772263},{"code":"ARS","rateInUsd":838.893582},{"code":"AUD","rateInUsd":1.52376},{"code":"AWG","rateInUsd":1.79},{"code":"AZN","rateInUsd":1.7},{"code":"BAM","rateInUsd":1.72786},{"code":"BBD","rateInUsd":2},{"code":"BDT","rateInUsd":109.589232},{"code":"BGN","rateInUsd":1.80075},{"code":"BHD","rateInUsd":0.376},{"code":"BIF","rateInUsd":2856.300177},{"code":"BMD","rateInUsd":1},{"code":"BND","rateInUsd":1.34197},{"code":"BOB","rateInUsd":6.932811},{"code":"BRL","rateInUsd":4.992911},{"code":"BSD","rateInUsd":1},{"code":"BTN","rateInUsd":82.711322},{"code":"BWP","rateInUsd":13.779672},{"code":"BYN","rateInUsd":3.273925},{"code":"BYR","rateInUsd":32739.234002},{"code":"BZD","rateInUsd":2},{"code":"CAD","rateInUsd":1.3502},{"code":"CDF","rateInUsd":2661.430439},{"code":"CHF","rateInUsd":0.88074},{"code":"CLF","rateInUsd":0.02627},{"code":"CLP","rateInUsd":982.175655},{"code":"CNY","rateInUsd":7.194161},{"code":"COP","rateInUsd":3963.831084},{"code":"CRC","rateInUsd":514.182697},{"code":"CUC","rateInUsd":1},{"code":"CUP","rateInUsd":24},{"code":"CVE","rateInUsd":101.873202},{"code":"CZK","rateInUsd":23.400613},{"code":"DJF","rateInUsd":177.721},{"code":"DKK","rateInUsd":6.887631},{"code":"DOP","rateInUsd":58.789301},{"code":"DZD","rateInUsd":135.091081},{"code":"EGP","rateInUsd":30.896673},{"code":"ERN","rateInUsd":15},{"code":"ETB","rateInUsd":56.764311},{"code":"EUR","rateInUsd":0.9238},{"code":"FJD","rateInUsd":2.2347},{"code":"FKP","rateInUsd":0.788834},{"code":"GBP","rateInUsd":0.78904},{"code":"GEL","rateInUsd":2.64792},{"code":"GGP","rateInUsd":0.788834},{"code":"GHS","rateInUsd":12.501892},{"code":"GIP","rateInUsd":0.788834},{"code":"GMD","rateInUsd":58.447569},{"code":"GNF","rateInUsd":8544.45582},{"code":"GTQ","rateInUsd":7.802991},{"code":"GYD","rateInUsd":208.874372},{"code":"HKD","rateInUsd":7.821451},{"code":"HNL","rateInUsd":24.676345},{"code":"HRK","rateInUsd":6.679631},{"code":"HTG","rateInUsd":134.466944},{"code":"HUF","rateInUsd":358.966731},{"code":"IDR","rateInUsd":15570.559218},{"code":"ILS","rateInUsd":3.62408},{"code":"IMP","rateInUsd":0.788834},{"code":"INR","rateInUsd":82.820204},{"code":"IQD","rateInUsd":1307.679199},{"code":"IRR","rateInUsd":41992.492796},{"code":"ISK","rateInUsd":136.974526},{"code":"JEP","rateInUsd":0.788835},{"code":"JMD","rateInUsd":154.384734},{"code":"JOD","rateInUsd":0.71},{"code":"JPY","rateInUsd":150.457664},{"code":"KES","rateInUsd":145.975137},{"code":"KGS","rateInUsd":89.478936},{"code":"KHR","rateInUsd":4068.41857},{"code":"KMF","rateInUsd":454.64674},{"code":"KPW","rateInUsd":900.010678},{"code":"KRW","rateInUsd":1328.391483},{"code":"KWD","rateInUsd":0.30748},{"code":"KYD","rateInUsd":0.83333},{"code":"KZT","rateInUsd":448.813325},{"code":"LAK","rateInUsd":20872.999373},{"code":"LBP","rateInUsd":89549.944743},{"code":"LKR","rateInUsd":310.471426},{"code":"LRD","rateInUsd":190.753255},{"code":"LSL","rateInUsd":19.186662},{"code":"LTL","rateInUsd":3.187958},{"code":"LVL","rateInUsd":0.648893},{"code":"LYD","rateInUsd":4.826841},{"code":"MAD","rateInUsd":10.045131},{"code":"MDL","rateInUsd":17.798342},{"code":"MGA","rateInUsd":4550.649152},{"code":"MKD","rateInUsd":56.942238},{"code":"MMK","rateInUsd":2094.559001},{"code":"MNT","rateInUsd":3391.598139},{"code":"MOP","rateInUsd":8.041201},{"code":"MRO","rateInUsd":356.999828},{"code":"MUR","rateInUsd":45.605597},{"code":"MVR","rateInUsd":15.446122},{"code":"MWK","rateInUsd":1683.026371},{"code":"MXN","rateInUsd":17.117552},{"code":"MYR","rateInUsd":4.774651},{"code":"MZN","rateInUsd":63.689812},{"code":"NAD","rateInUsd":19.270534},{"code":"NGN","rateInUsd":1488.653857},{"code":"NIO","rateInUsd":36.823494},{"code":"NOK","rateInUsd":10.538761},{"code":"NPR","rateInUsd":132.554306},{"code":"NZD","rateInUsd":1.61345},{"code":"OMR","rateInUsd":0.38391},{"code":"PAB","rateInUsd":0.99886},{"code":"PEN","rateInUsd":3.797031},{"code":"PGK","rateInUsd":3.777131},{"code":"PHP","rateInUsd":55.886419},{"code":"PKR","rateInUsd":279.334256},{"code":"PLN","rateInUsd":3.9763},{"code":"PYG","rateInUsd":7297.304115},{"code":"QAR","rateInUsd":3.6392},{"code":"RON","rateInUsd":4.595551},{"code":"RSD","rateInUsd":107.880962},{"code":"RUB","rateInUsd":94.739477},{"code":"RWF","rateInUsd":1275.699236},{"code":"SAR","rateInUsd":3.744281},{"code":"SBD","rateInUsd":8.229024},{"code":"SCR","rateInUsd":14.446013},{"code":"SDG","rateInUsd":601.5},{"code":"SEK","rateInUsd":10.316012},{"code":"SGD","rateInUsd":1.34188},{"code":"SHP","rateInUsd":0.78904},{"code":"SLL","rateInUsd":22710.047194},{"code":"SOS","rateInUsd":571.331816},{"code":"SRD","rateInUsd":35.498124},{"code":"STD","rateInUsd":22842.625705},{"code":"SVC","rateInUsd":8.75},{"code":"SYP","rateInUsd":13001.90745},{"code":"SZL","rateInUsd":19.302332},{"code":"THB","rateInUsd":35.905826},{"code":"TJS","rateInUsd":10.944091},{"code":"TMT","rateInUsd":3.5},{"code":"TND","rateInUsd":3.11342},{"code":"TOP","rateInUsd":2.34856},{"code":"TRY","rateInUsd":30.966104},{"code":"TTD","rateInUsd":6.790161},{"code":"TWD","rateInUsd":31.622275},{"code":"TZS","rateInUsd":2546.901133},{"code":"UAH","rateInUsd":38.599615},{"code":"UGX","rateInUsd":3868.711907},{"code":"USD","rateInUsd":1},{"code":"UYU","rateInUsd":38.510138},{"code":"UZS","rateInUsd":12505.99847},{"code":"VEF","rateInUsd":3610627.557427},{"code":"VND","rateInUsd":24624.261099},{"code":"VUV","rateInUsd":119.198013},{"code":"WST","rateInUsd":2.731514},{"code":"XAF","rateInUsd":606.116745},{"code":"XCD","rateInUsd":2.7},{"code":"XOF","rateInUsd":606.116762},{"code":"XPF","rateInUsd":110.151039},{"code":"YER","rateInUsd":249.790156},{"code":"ZAR","rateInUsd":19.290893},{"code":"ZMK","rateInUsd":9001.2},{"code":"ZMW","rateInUsd":23.038842},{"code":"ZWL","rateInUsd":361.9}],"updatedAt":1708783207705}