{"arg":[{"code":"EUR","rateInArs":907.91,"rateDetails":{"buy":907.69,"sell":908.13,"average":907.91}},{"code":"USD","rateInArs":839.5,"rateDetails":{"buy":819.5,"sell":859.5,"average":839.5}},{"code":"USD_BLUE","rateInArs":1070,"rateDetails":{"buy":1060,"sell":1080,"average":1070}},{"code":"USD_MEP","rateInArs":1049.45,"rateDetails":{"buy":1046.7,"sell":1052.2,"average":1049.45}},{"code":"USD_CCL","rateInArs":1087.05,"rateDetails":{"buy":1086.6,"sell":1087.5,"average":1087.05}}],"all":[{"code":"AED","rateInUsd":3.671721},{"code":"AFN","rateInUsd":73.711581},{"code":"ALL","rateInUsd":95.764434},{"code":"AMD","rateInUsd":404.686976},{"code":"ANG","rateInUsd":1.78615},{"code":"AOA","rateInUsd":829.756491},{"code":"ARS","rateInUsd":839.303875},{"code":"AUD","rateInUsd":1.523},{"code":"AWG","rateInUsd":1.79},{"code":"AZN","rateInUsd":1.7},{"code":"BAM","rateInUsd":1.72786},{"code":"BBD","rateInUsd":2},{"code":"BDT","rateInUsd":109.67131},{"code":"BGN","rateInUsd":1.80154},{"code":"BHD","rateInUsd":0.376},{"code":"BIF","rateInUsd":2858.643646},{"code":"BMD","rateInUsd":1},{"code":"BND","rateInUsd":1.34217},{"code":"BOB","rateInUsd":6.937281},{"code":"BRL","rateInUsd":4.993981},{"code":"BSD","rateInUsd":1},{"code":"BTN","rateInUsd":82.706579},{"code":"BWP","rateInUsd":13.779672},{"code":"BYN","rateInUsd":3.27018},{"code":"BYR","rateInUsd":32701.779124},{"code":"BZD","rateInUsd":2},{"code":"CAD","rateInUsd":1.35048},{"code":"CDF","rateInUsd":2661.367394},{"code":"CHF","rateInUsd":0.88103},{"code":"CLF","rateInUsd":0.02627},{"code":"CLP","rateInUsd":981.907398},{"code":"CNY","rateInUsd":7.198321},{"code":"COP","rateInUsd":3960.714143},{"code":"CRC","rateInUsd":514.454004},{"code":"CUC","rateInUsd":1},{"code":"CUP","rateInUsd":24},{"code":"CVE","rateInUsd":101.890556},{"code":"CZK","rateInUsd":23.344273},{"code":"DJF","rateInUsd":177.721},{"code":"DKK","rateInUsd":6.887621},{"code":"DOP","rateInUsd":58.632518},{"code":"DZD","rateInUsd":135.1826},{"code":"EGP","rateInUsd":31.017316},{"code":"ERN","rateInUsd":15},{"code":"ETB","rateInUsd":56.748681},{"code":"EUR","rateInUsd":0.92416},{"code":"FJD","rateInUsd":2.2362},{"code":"FKP","rateInUsd":0.789134},{"code":"GBP","rateInUsd":0.78904},{"code":"GEL","rateInUsd":2.64792},{"code":"GGP","rateInUsd":0.789134},{"code":"GHS","rateInUsd":12.507342},{"code":"GIP","rateInUsd":0.789134},{"code":"GMD","rateInUsd":58.447568},{"code":"GNF","rateInUsd":8555.029311},{"code":"GTQ","rateInUsd":7.807501},{"code":"GYD","rateInUsd":209.02193},{"code":"HKD","rateInUsd":7.821451},{"code":"HNL","rateInUsd":24.698663},{"code":"HRK","rateInUsd":6.679631},{"code":"HTG","rateInUsd":134.560837},{"code":"HUF","rateInUsd":359.156877},{"code":"IDR","rateInUsd":15582.946831},{"code":"ILS","rateInUsd":3.636321},{"code":"IMP","rateInUsd":0.789134},{"code":"INR","rateInUsd":82.884123},{"code":"IQD","rateInUsd":1308.886365},{"code":"IRR","rateInUsd":42019.714998},{"code":"ISK","rateInUsd":136.961107},{"code":"JEP","rateInUsd":0.789134},{"code":"JMD","rateInUsd":156.471743},{"code":"JOD","rateInUsd":0.71},{"code":"JPY","rateInUsd":150.468712},{"code":"KES","rateInUsd":143.373675},{"code":"KGS","rateInUsd":89.463942},{"code":"KHR","rateInUsd":4065.846282},{"code":"KMF","rateInUsd":455.058632},{"code":"KPW","rateInUsd":900.020399},{"code":"KRW","rateInUsd":1328.186398},{"code":"KWD","rateInUsd":0.30772},{"code":"KYD","rateInUsd":0.83333},{"code":"KZT","rateInUsd":449.136862},{"code":"LAK","rateInUsd":20887.202611},{"code":"LBP","rateInUsd":89614.642057},{"code":"LKR","rateInUsd":310.446963},{"code":"LRD","rateInUsd":190.753241},{"code":"LSL","rateInUsd":19.185472},{"code":"LTL","rateInUsd":3.191135},{"code":"LVL","rateInUsd":0.64954},{"code":"LYD","rateInUsd":4.829631},{"code":"MAD","rateInUsd":10.050972},{"code":"MDL","rateInUsd":17.796363},{"code":"MGA","rateInUsd":4554.610172},{"code":"MKD","rateInUsd":56.98216},{"code":"MMK","rateInUsd":2094.361763},{"code":"MNT","rateInUsd":3406.098748},{"code":"MOP","rateInUsd":8.041201},{"code":"MRO","rateInUsd":356.999828},{"code":"MUR","rateInUsd":45.637949},{"code":"MVR","rateInUsd":15.457803},{"code":"MWK","rateInUsd":1684.107398},{"code":"MXN","rateInUsd":17.107373},{"code":"MYR","rateInUsd":4.777611},{"code":"MZN","rateInUsd":63.723971},{"code":"NAD","rateInUsd":19.277243},{"code":"NGN","rateInUsd":1489.81372},{"code":"NIO","rateInUsd":36.778101},{"code":"NOK","rateInUsd":10.530472},{"code":"NPR","rateInUsd":132.50775},{"code":"NZD","rateInUsd":1.61596},{"code":"OMR","rateInUsd":0.3843},{"code":"PAB","rateInUsd":0.99886},{"code":"PEN","rateInUsd":3.799951},{"code":"PGK","rateInUsd":3.77638},{"code":"PHP","rateInUsd":55.921451},{"code":"PKR","rateInUsd":279.274291},{"code":"PLN","rateInUsd":3.975041},{"code":"PYG","rateInUsd":7302.038334},{"code":"QAR","rateInUsd":3.64112},{"code":"RON","rateInUsd":4.59663},{"code":"RSD","rateInUsd":107.880963},{"code":"RUB","rateInUsd":94.739471},{"code":"RWF","rateInUsd":1275.438917},{"code":"SAR","rateInUsd":3.746281},{"code":"SBD","rateInUsd":8.298482},{"code":"SCR","rateInUsd":14.454382},{"code":"SDG","rateInUsd":601.5},{"code":"SEK","rateInUsd":10.322402},{"code":"SGD","rateInUsd":1.34309},{"code":"SHP","rateInUsd":0.78904},{"code":"SLL","rateInUsd":22728.194201},{"code":"SOS","rateInUsd":571.409944},{"code":"SRD","rateInUsd":35.524006},{"code":"STD","rateInUsd":22686.223239},{"code":"SVC","rateInUsd":8.75},{"code":"SYP","rateInUsd":13001.868919},{"code":"SZL","rateInUsd":19.276374},{"code":"THB","rateInUsd":35.953954},{"code":"TJS","rateInUsd":10.943772},{"code":"TMT","rateInUsd":3.5},{"code":"TND","rateInUsd":3.11539},{"code":"TOP","rateInUsd":2.33717},{"code":"TRY","rateInUsd":31.084855},{"code":"TTD","rateInUsd":6.794651},{"code":"TWD","rateInUsd":31.582985},{"code":"TZS","rateInUsd":2548.510775},{"code":"UAH","rateInUsd":38.629366},{"code":"UGX","rateInUsd":3871.047578},{"code":"USD","rateInUsd":1},{"code":"UYU","rateInUsd":38.540755},{"code":"UZS","rateInUsd":12511.521375},{"code":"VEF","rateInUsd":3610738.827379},{"code":"VND","rateInUsd":24642.173388},{"code":"VUV","rateInUsd":120.058424},{"code":"WST","rateInUsd":2.729641},{"code":"XAF","rateInUsd":606.036279},{"code":"XCD","rateInUsd":2.7},{"code":"XOF","rateInUsd":606.036231},{"code":"XPF","rateInUsd":110.193648},{"code":"YER","rateInUsd":249.99688},{"code":"ZAR","rateInUsd":19.301382},{"code":"ZMK","rateInUsd":9001.2},{"code":"ZMW","rateInUsd":23.054074},{"code":"ZWL","rateInUsd":361.9}],"updatedAt":1708977607914}