{"arg":[{"code":"EUR","rateInArs":1065.477,"rateDetails":{"buy":1062.623,"sell":1068.331,"average":1065.477}},{"code":"USD","rateInArs":987.5,"rateDetails":{"buy":967.5,"sell":1007.5,"average":987.5}},{"code":"USD_BLUE","rateInArs":1210,"rateDetails":{"buy":1200,"sell":1220,"average":1210}},{"code":"USD_MEP","rateInArs":1149.3,"rateDetails":{"buy":1148.3,"sell":1150.3,"average":1149.3}},{"code":"USD_CCL","rateInArs":1166,"rateDetails":{"buy":1165.4,"sell":1166.6,"average":1166}}],"all":[{"code":"AED","rateInUsd":3.671681},{"code":"AFN","rateInUsd":66.531163},{"code":"ALL","rateInUsd":91.199722},{"code":"AMD","rateInUsd":387.047862},{"code":"ANG","rateInUsd":1.78604},{"code":"AOA","rateInUsd":909.461052},{"code":"ARS","rateInUsd":984.759968},{"code":"AUD","rateInUsd":1.50715},{"code":"AWG","rateInUsd":1.79},{"code":"AZN","rateInUsd":1.7},{"code":"BAM","rateInUsd":1.80523},{"code":"BBD","rateInUsd":2},{"code":"BDT","rateInUsd":119.963322},{"code":"BGN","rateInUsd":1.80725},{"code":"BHD","rateInUsd":0.376},{"code":"BIF","rateInUsd":2895.578002},{"code":"BMD","rateInUsd":1},{"code":"BND","rateInUsd":1.31765},{"code":"BOB","rateInUsd":6.923071},{"code":"BRL","rateInUsd":5.665801},{"code":"BSD","rateInUsd":1},{"code":"BTN","rateInUsd":84.008239},{"code":"BWP","rateInUsd":13.408422},{"code":"BYN","rateInUsd":3.270181},{"code":"BYR","rateInUsd":32701.779565},{"code":"BZD","rateInUsd":2},{"code":"CAD","rateInUsd":1.38504},{"code":"CDF","rateInUsd":2839.936335},{"code":"CHF","rateInUsd":0.86571},{"code":"CLF","rateInUsd":0.02452},{"code":"CLP","rateInUsd":946.694246},{"code":"CNY","rateInUsd":7.118241},{"code":"COP","rateInUsd":4299.993599},{"code":"CRC","rateInUsd":515.042338},{"code":"CUC","rateInUsd":1},{"code":"CUP","rateInUsd":24},{"code":"CVE","rateInUsd":101.853963},{"code":"CZK","rateInUsd":23.256793},{"code":"DJF","rateInUsd":177.721},{"code":"DKK","rateInUsd":6.890001},{"code":"DOP","rateInUsd":60.174379},{"code":"DZD","rateInUsd":133.718796},{"code":"EGP","rateInUsd":48.777247},{"code":"ERN","rateInUsd":15},{"code":"ETB","rateInUsd":119.666543},{"code":"EUR","rateInUsd":0.92378},{"code":"FJD","rateInUsd":2.24239},{"code":"FKP","rateInUsd":0.77097},{"code":"GBP","rateInUsd":0.77087},{"code":"GEL","rateInUsd":2.70563},{"code":"GGP","rateInUsd":0.77097},{"code":"GHS","rateInUsd":16.052903},{"code":"GIP","rateInUsd":0.770969},{"code":"GMD","rateInUsd":57.101759},{"code":"GNF","rateInUsd":8615.820948},{"code":"GTQ","rateInUsd":7.723531},{"code":"GYD","rateInUsd":208.869697},{"code":"HKD","rateInUsd":7.768401},{"code":"HNL","rateInUsd":24.928814},{"code":"HRK","rateInUsd":6.525821},{"code":"HTG","rateInUsd":133.472103},{"code":"HUF","rateInUsd":372.062823},{"code":"IDR","rateInUsd":15557.30562},{"code":"ILS","rateInUsd":3.78941},{"code":"IMP","rateInUsd":0.77097},{"code":"INR","rateInUsd":84.04756},{"code":"IQD","rateInUsd":1307.956336},{"code":"IRR","rateInUsd":42005.895959},{"code":"ISK","rateInUsd":137.355766},{"code":"JEP","rateInUsd":0.77097},{"code":"JMD","rateInUsd":157.914968},{"code":"JOD","rateInUsd":0.71},{"code":"JPY","rateInUsd":151.789607},{"code":"KES","rateInUsd":128.966628},{"code":"KGS","rateInUsd":85.755809},{"code":"KHR","rateInUsd":4055.472562},{"code":"KMF","rateInUsd":456.041798},{"code":"KPW","rateInUsd":899.995894},{"code":"KRW","rateInUsd":1376.301955},{"code":"KWD","rateInUsd":0.30619},{"code":"KYD","rateInUsd":0.83333},{"code":"KZT","rateInUsd":485.489942},{"code":"LAK","rateInUsd":21937.439178},{"code":"LBP","rateInUsd":89544.657423},{"code":"LKR","rateInUsd":293.418335},{"code":"LRD","rateInUsd":192.387668},{"code":"LSL","rateInUsd":17.659942},{"code":"LTL","rateInUsd":3.190023},{"code":"LVL","rateInUsd":0.649313},{"code":"LYD","rateInUsd":4.813351},{"code":"MAD","rateInUsd":9.856852},{"code":"MDL","rateInUsd":17.897442},{"code":"MGA","rateInUsd":4605.359873},{"code":"MKD","rateInUsd":57.012406},{"code":"MMK","rateInUsd":2097.99376},{"code":"MNT","rateInUsd":3408.618736},{"code":"MOP","rateInUsd":7.980701},{"code":"MRO","rateInUsd":356.999828},{"code":"MUR","rateInUsd":46.168228},{"code":"MVR","rateInUsd":15.450002},{"code":"MWK","rateInUsd":1733.416891},{"code":"MXN","rateInUsd":19.824862},{"code":"MYR","rateInUsd":4.34093},{"code":"MZN","rateInUsd":63.572548},{"code":"NAD","rateInUsd":17.620703},{"code":"NGN","rateInUsd":1650.771428},{"code":"NIO","rateInUsd":36.797779},{"code":"NOK","rateInUsd":10.937382},{"code":"NPR","rateInUsd":134.413355},{"code":"NZD","rateInUsd":1.66405},{"code":"OMR","rateInUsd":0.38397},{"code":"PAB","rateInUsd":0.99887},{"code":"PEN","rateInUsd":3.754701},{"code":"PGK","rateInUsd":3.949951},{"code":"PHP","rateInUsd":57.912019},{"code":"PKR","rateInUsd":277.580721},{"code":"PLN","rateInUsd":4.012281},{"code":"PYG","rateInUsd":7977.152677},{"code":"QAR","rateInUsd":3.638991},{"code":"RON","rateInUsd":4.593101},{"code":"RSD","rateInUsd":107.964681},{"code":"RUB","rateInUsd":95.476537},{"code":"RWF","rateInUsd":1351.97325},{"code":"SAR","rateInUsd":3.736481},{"code":"SBD","rateInUsd":8.370702},{"code":"SCR","rateInUsd":14.896201},{"code":"SDG","rateInUsd":601.5},{"code":"SEK","rateInUsd":10.559811},{"code":"SGD","rateInUsd":1.31833},{"code":"SHP","rateInUsd":0.77087},{"code":"SLL","rateInUsd":22646.87354},{"code":"SOS","rateInUsd":570.899602},{"code":"SRD","rateInUsd":33.539236},{"code":"STD","rateInUsd":22824.124764},{"code":"SVC","rateInUsd":8.75},{"code":"SYP","rateInUsd":13005.761257},{"code":"SZL","rateInUsd":17.656623},{"code":"THB","rateInUsd":33.680534},{"code":"TJS","rateInUsd":10.627652},{"code":"TMT","rateInUsd":3.5},{"code":"TND","rateInUsd":3.1131},{"code":"TOP","rateInUsd":2.3467},{"code":"TRY","rateInUsd":34.280667},{"code":"TTD","rateInUsd":6.802281},{"code":"TWD","rateInUsd":32.016766},{"code":"TZS","rateInUsd":2717.012879},{"code":"UAH","rateInUsd":41.390965},{"code":"UGX","rateInUsd":3663.737752},{"code":"USD","rateInUsd":1},{"code":"UYU","rateInUsd":41.630327},{"code":"UZS","rateInUsd":12849.766469},{"code":"VEF","rateInUsd":4082773.636925},{"code":"VND","rateInUsd":25376.767582},{"code":"VUV","rateInUsd":119.846247},{"code":"WST","rateInUsd":2.751399},{"code":"XAF","rateInUsd":605.962044},{"code":"XCD","rateInUsd":2.7},{"code":"XOF","rateInUsd":605.962025},{"code":"XPF","rateInUsd":110.130064},{"code":"YER","rateInUsd":249.810013},{"code":"ZAR","rateInUsd":17.651152},{"code":"ZMK","rateInUsd":9001.2},{"code":"ZMW","rateInUsd":26.586575},{"code":"ZWL","rateInUsd":68537.253618}],"updatedAt":1729882812850}