{"arg":[{"code":"EUR","rateInArs":1005.81,"rateDetails":{"buy":1005.22,"sell":1006.4,"average":1005.81}},{"code":"USD","rateInArs":926.5,"rateDetails":{"buy":906.5,"sell":946.5,"average":926.5}},{"code":"USD_BLUE","rateInArs":1440,"rateDetails":{"buy":1430,"sell":1450,"average":1440}},{"code":"USD_MEP","rateInArs":1335.05,"rateDetails":{"buy":1332,"sell":1338.1,"average":1335.05}},{"code":"USD_CCL","rateInArs":1336.6,"rateDetails":{"buy":1335.7,"sell":1337.5,"average":1336.6}}],"all":[{"code":"AED","rateInUsd":3.672261},{"code":"AFN","rateInUsd":70.82672},{"code":"ALL","rateInUsd":92.611125},{"code":"AMD","rateInUsd":388.453592},{"code":"ANG","rateInUsd":1.7868},{"code":"AOA","rateInUsd":874.389748},{"code":"ARS","rateInUsd":927.413378},{"code":"AUD","rateInUsd":1.52067},{"code":"AWG","rateInUsd":1.79},{"code":"AZN","rateInUsd":1.7},{"code":"BAM","rateInUsd":1.80395},{"code":"BBD","rateInUsd":2},{"code":"BDT","rateInUsd":117.947893},{"code":"BGN","rateInUsd":1.80159},{"code":"BHD","rateInUsd":0.376},{"code":"BIF","rateInUsd":2881.799785},{"code":"BMD","rateInUsd":1},{"code":"BND","rateInUsd":1.34229},{"code":"BOB","rateInUsd":6.909721},{"code":"BRL","rateInUsd":5.655091},{"code":"BSD","rateInUsd":1},{"code":"BTN","rateInUsd":83.888301},{"code":"BWP","rateInUsd":13.603923},{"code":"BYN","rateInUsd":3.270022},{"code":"BYR","rateInUsd":32700.224202},{"code":"BZD","rateInUsd":2},{"code":"CAD","rateInUsd":1.38051},{"code":"CDF","rateInUsd":2832.419127},{"code":"CHF","rateInUsd":0.88486},{"code":"CLF","rateInUsd":0.02488},{"code":"CLP","rateInUsd":948.42591},{"code":"CNY","rateInUsd":7.259481},{"code":"COP","rateInUsd":4040.227628},{"code":"CRC","rateInUsd":527.690129},{"code":"CUC","rateInUsd":1},{"code":"CUP","rateInUsd":24},{"code":"CVE","rateInUsd":101.739301},{"code":"CZK","rateInUsd":23.425183},{"code":"DJF","rateInUsd":177.721},{"code":"DKK","rateInUsd":6.882301},{"code":"DOP","rateInUsd":59.173378},{"code":"DZD","rateInUsd":135.098227},{"code":"EGP","rateInUsd":48.325127},{"code":"ERN","rateInUsd":15},{"code":"ETB","rateInUsd":57.845888},{"code":"EUR","rateInUsd":0.92234},{"code":"FJD","rateInUsd":2.25507},{"code":"FKP","rateInUsd":0.775216},{"code":"GBP","rateInUsd":0.77509},{"code":"GEL","rateInUsd":2.72046},{"code":"GGP","rateInUsd":0.775216},{"code":"GHS","rateInUsd":15.458003},{"code":"GIP","rateInUsd":0.775216},{"code":"GMD","rateInUsd":57.413776},{"code":"GNF","rateInUsd":8598.879124},{"code":"GTQ","rateInUsd":7.743571},{"code":"GYD","rateInUsd":208.887937},{"code":"HKD","rateInUsd":7.805731},{"code":"HNL","rateInUsd":24.761582},{"code":"HRK","rateInUsd":6.561481},{"code":"HTG","rateInUsd":134.150289},{"code":"HUF","rateInUsd":362.706818},{"code":"IDR","rateInUsd":16195.261628},{"code":"ILS","rateInUsd":3.64703},{"code":"IMP","rateInUsd":0.775216},{"code":"INR","rateInUsd":83.696081},{"code":"IQD","rateInUsd":1308.554075},{"code":"IRR","rateInUsd":42015.152209},{"code":"ISK","rateInUsd":138.142761},{"code":"JEP","rateInUsd":0.775216},{"code":"JMD","rateInUsd":156.268144},{"code":"JOD","rateInUsd":0.71},{"code":"JPY","rateInUsd":153.853745},{"code":"KES","rateInUsd":132.467101},{"code":"KGS","rateInUsd":84.253376},{"code":"KHR","rateInUsd":4099.227085},{"code":"KMF","rateInUsd":453.569354},{"code":"KPW","rateInUsd":899.996364},{"code":"KRW","rateInUsd":1378.90863},{"code":"KWD","rateInUsd":0.30576},{"code":"KYD","rateInUsd":0.83333},{"code":"KZT","rateInUsd":472.248146},{"code":"LAK","rateInUsd":22178.923877},{"code":"LBP","rateInUsd":89535.581579},{"code":"LKR","rateInUsd":303.218973},{"code":"LRD","rateInUsd":195.381284},{"code":"LSL","rateInUsd":18.354572},{"code":"LTL","rateInUsd":3.185495},{"code":"LVL","rateInUsd":0.648391},{"code":"LYD","rateInUsd":4.832621},{"code":"MAD","rateInUsd":9.892961},{"code":"MDL","rateInUsd":17.699782},{"code":"MGA","rateInUsd":4541.785709},{"code":"MKD","rateInUsd":56.680709},{"code":"MMK","rateInUsd":2094.37474},{"code":"MNT","rateInUsd":3398.072106},{"code":"MOP","rateInUsd":8.028341},{"code":"MRO","rateInUsd":356.999828},{"code":"MUR","rateInUsd":46.716899},{"code":"MVR","rateInUsd":15.448702},{"code":"MWK","rateInUsd":1734.037401},{"code":"MXN","rateInUsd":18.352872},{"code":"MYR","rateInUsd":4.672771},{"code":"MZN","rateInUsd":63.610509},{"code":"NAD","rateInUsd":18.316442},{"code":"NGN","rateInUsd":1541.808418},{"code":"NIO","rateInUsd":36.831814},{"code":"NOK","rateInUsd":11.025212},{"code":"NPR","rateInUsd":133.880564},{"code":"NZD","rateInUsd":1.68681},{"code":"OMR","rateInUsd":0.3842},{"code":"PAB","rateInUsd":0.99899},{"code":"PEN","rateInUsd":3.778421},{"code":"PGK","rateInUsd":3.8631},{"code":"PHP","rateInUsd":58.57657},{"code":"PKR","rateInUsd":278.513135},{"code":"PLN","rateInUsd":3.962011},{"code":"PYG","rateInUsd":7601.235317},{"code":"QAR","rateInUsd":3.640631},{"code":"RON","rateInUsd":4.583861},{"code":"RSD","rateInUsd":107.598956},{"code":"RUB","rateInUsd":86.177914},{"code":"RWF","rateInUsd":1311.080816},{"code":"SAR","rateInUsd":3.74999},{"code":"SBD","rateInUsd":8.332194},{"code":"SCR","rateInUsd":14.727562},{"code":"SDG","rateInUsd":601.5},{"code":"SEK","rateInUsd":10.773612},{"code":"SGD","rateInUsd":1.34347},{"code":"SHP","rateInUsd":0.77509},{"code":"SLL","rateInUsd":22424.782072},{"code":"SOS","rateInUsd":571.298682},{"code":"SRD","rateInUsd":29.111054},{"code":"STD","rateInUsd":22827.029038},{"code":"SVC","rateInUsd":8.75},{"code":"SYP","rateInUsd":13001.838964},{"code":"SZL","rateInUsd":18.350543},{"code":"THB","rateInUsd":36.109545},{"code":"TJS","rateInUsd":10.648201},{"code":"TMT","rateInUsd":3.5},{"code":"TND","rateInUsd":3.09969},{"code":"TOP","rateInUsd":2.3563},{"code":"TRY","rateInUsd":32.818136},{"code":"TTD","rateInUsd":6.793181},{"code":"TWD","rateInUsd":32.760556},{"code":"TZS","rateInUsd":2687.105977},{"code":"UAH","rateInUsd":41.371055},{"code":"UGX","rateInUsd":3717.210408},{"code":"USD","rateInUsd":1},{"code":"UYU","rateInUsd":40.223697},{"code":"UZS","rateInUsd":12641.571304},{"code":"VEF","rateInUsd":3651344.106747},{"code":"VND","rateInUsd":25355.845903},{"code":"VUV","rateInUsd":119.877312},{"code":"WST","rateInUsd":2.744046},{"code":"XAF","rateInUsd":605.018006},{"code":"XCD","rateInUsd":2.7},{"code":"XOF","rateInUsd":605.017975},{"code":"XPF","rateInUsd":109.987},{"code":"YER","rateInUsd":249.916331},{"code":"ZAR","rateInUsd":18.354343},{"code":"ZMK","rateInUsd":9001.2},{"code":"ZMW","rateInUsd":26.099853},{"code":"ZWL","rateInUsd":34383.6686}],"updatedAt":1721869204368}